lifecycle/__init__.py
lifecycle/cli.py
lifecycle/config_reader.py
lifecycle/model_diff.py
lifecycle/models.py
lifecycle/source_ldap3.py
lifecycle/source_staticconfig.py
lifecycle/target_suitecrm.py
ct_lifecycle-0.1.4.dist-info/LICENSE
ct_lifecycle-0.1.4.dist-info/METADATA
ct_lifecycle-0.1.4.dist-info/WHEEL
ct_lifecycle-0.1.4.dist-info/entry_points.txt
ct_lifecycle-0.1.4.dist-info/top_level.txt
ct_lifecycle-0.1.4.dist-info/RECORD
