Metadata-Version: 2.1
Name: ct-lifecycle
Version: 0.1.4
Summary: Assert the SSOT principle for users and groups across disparate applications and services.
License: MIT
Classifier: Programming Language :: Python :: 3
Requires-Python: >=3.7
License-File: LICENSE
Requires-Dist: addict
Requires-Dist: ldap3
Requires-Dist: PyJWT
Requires-Dist: pyyaml
Requires-Dist: requests
Provides-Extra: dev
Requires-Dist: pre-commit ; extra == 'dev'
Requires-Dist: pylint ; extra == 'dev'
Requires-Dist: pytest ; extra == 'dev'
Requires-Dist: pytest-cov ; extra == 'dev'
Requires-Dist: pytest-mock ; extra == 'dev'
Requires-Dist: pytest-pylint ; extra == 'dev'
Requires-Dist: black ; extra == 'dev'
